Metadata-Version: 1.1
Name: offer
Version: 0.2.1
Summary: Quickly host files for local transfer.
Home-page: https://github.com/musically-ut/offer
Author: Utkarsh Upadhyay
Author-email: musically.ut@gmail.com
License: MIT
Keywords: host,network,local
Platform: UNKNOWN
Classifier: Development Status :: 4 - Beta
Classifier: Intended Audience :: Developers
Classifier: License :: OSI Approved :: MIT License
Classifier: Natural Language :: English
Classifier: Operating System :: Unix
Classifier: Programming Language :: Python :: 2.7
Classifier: Programming Language :: Python :: 3.4
Classifier: Programming Language :: Python :: 3.5
Classifier: Operating System :: OS Independent
